cpln/__init__.py
cpln/_version.py
cpln/api/__init__.py
cpln/api/client.py
cpln/api/config.py
cpln/api/gvc.py
cpln/api/image.py
cpln/api/workload.py
cpln/client.py
cpln/config/__init__.py
cpln/config/workload.py
cpln/constants.py
cpln/errors.py
cpln/exceptions.py
cpln/models/__init__.py
cpln/models/gvcs.py
cpln/models/images.py
cpln/models/resource.py
cpln/models/workloads.py
cpln/parsers/__init__.py
cpln/parsers/base.py
cpln/parsers/container.py
cpln/parsers/deployment.py
cpln/parsers/spec.py
cpln/py.typed
cpln/templates/default-serverless-workload.json
cpln/templates/default-standard-workload.json
cpln/utils/__init__.py
cpln/utils/exit_codes/__init__.py
cpln/utils/exit_codes/aws.py
cpln/utils/exit_codes/generic.py
cpln/utils/exit_codes/postgres.py
cpln/utils/utils.py
cpln/utils/websocket.py
cpln/version.py
cpln_py-1.2.4.dist-info/METADATA
cpln_py-1.2.4.dist-info/WHEEL
cpln_py-1.2.4.dist-info/entry_points.txt
cpln_py-1.2.4.dist-info/RECORD
