Metadata-Version: 2.1
Name: cpln-py
Version: 1.2.4
Summary: A Python library for the Control Plane API
Author-Email: dave6892 <dave6892@gmail.com>
License: Apache License 2.0
Classifier: Programming Language :: Python :: 3.9
Classifier: Programming Language :: Python :: 3.10
Classifier: Programming Language :: Python :: 3.11
Classifier: Programming Language :: Python :: 3.12
Classifier: Programming Language :: Python :: 3.13
Requires-Python: <3.14,>=3.9
Requires-Dist: python-dotenv>=1.0.1
Requires-Dist: requests>=2.32.3
Requires-Dist: websocket-client>=1.8.0
Requires-Dist: urllib3<2.0.0
Requires-Dist: inflection>=0.5.1
Provides-Extra: test
Requires-Dist: pytest>=8.4.0; extra == "test"
Requires-Dist: pytest-cov>=6.1.1; extra == "test"
Requires-Dist: requests-mock>=1.12.1; extra == "test"
Provides-Extra: docs
Requires-Dist: mkdocs>=1.6.1; extra == "docs"
Requires-Dist: mkdocstrings[python]>=0.29.1; extra == "docs"
Provides-Extra: lint
Requires-Dist: flake8>=7.2.0; extra == "lint"
Requires-Dist: black>=25.1.0; extra == "lint"
Requires-Dist: mypy>=1.9.0; extra == "lint"
Requires-Dist: types-requests>=2.31.0.1; extra == "lint"
